falfilfa4py/FA.py
falfilfa4py/LFA.py
falfilfa4py/LFI.py
falfilfa4py/__init__.py
falfilfa4py/include/facilo.h
falfilfa4py/include/facilo_mt.h
falfilfa4py/include/facono.h
falfilfa4py/include/facono_mt.h
falfilfa4py/include/faddate.h
falfilfa4py/include/fadoco.h
falfilfa4py/include/faieno.h
falfilfa4py/include/faieno_mt.h
falfilfa4py/include/falgra.h
falfilfa4py/lib64/libfa_dp.so
falfilfa4py/lib64/cmake/falfilfa/falfilfa-config-version.cmake
falfilfa4py/lib64/cmake/falfilfa/falfilfa-config.cmake
falfilfa4py/lib64/cmake/falfilfa/falfilfa-import.cmake
falfilfa4py/lib64/cmake/falfilfa/falfilfa-targets-debug.cmake
falfilfa4py/lib64/cmake/falfilfa/falfilfa-targets.cmake
falfilfa4py/module/eccodes_interface.mod
falfilfa4py/module/fa_mod.mod
falfilfa4py/module/fadup_mod.mod
falfilfa4py/module/lfagen.mod
falfilfa4py/module/lfi_precision.mod
falfilfa4py/module/lfimod.mod
falfilfa4py/module/modd_comppar.mod
falfilfa4py/module/mode_searchgrp.mod
falfilfa4py/module/yomlfa.mod
falfilfa4py-1.0.7.data/data/share/lfi_
falfilfa4py-1.0.7.dist-info/METADATA
falfilfa4py-1.0.7.dist-info/WHEEL
falfilfa4py-1.0.7.dist-info/top_level.txt
falfilfa4py-1.0.7.dist-info/RECORD
falfilfa4py.libs/libeccodes_f90-34ba42c0.so
falfilfa4py.libs/libparkind_dp-83af44ec.so
falfilfa4py.libs/libquadmath-96973f99.so.0.0.0
falfilfa4py.libs/libgfortran-040039e1.so.5.0.0
falfilfa4py.libs/libaec-2d6eebbf.so.0.1.3
falfilfa4py.libs/libeccodes_memfs-2babbcc9.so
falfilfa4py.libs/libfiat-a0e5fa54.so
falfilfa4py.libs/libeccodes-12c9289e.so
