Metadata-Version: 2.4
Name: falfilfa4py
Version: 1.0.7
Summary: FA/LFI/LFA for Python
Classifier: Development Status :: 3 - Alpha
Classifier: Intended Audience :: Science/Research
Classifier: Programming Language :: Python
Classifier: Programming Language :: Python :: 3.10
Classifier: Programming Language :: Python :: 3.11
Classifier: Programming Language :: Python :: 3.12
Classifier: Operating System :: Unix
Requires-Python: >=3.10
Requires-Dist: ctypesForFortran<2.0.0
Requires-Dist: numpy
